receptor_catalog/__init__.py
receptor_catalog/worker.py
receptor_catalog-0.6.3.dist-info/LICENSE.md
receptor_catalog-0.6.3.dist-info/METADATA
receptor_catalog-0.6.3.dist-info/WHEEL
receptor_catalog-0.6.3.dist-info/entry_points.txt
receptor_catalog-0.6.3.dist-info/top_level.txt
receptor_catalog-0.6.3.dist-info/RECORD
