Metadata-Version: 2.1
Name: receptor-catalog
Version: 0.6.3
Summary: Receptor plugin to communicate with Ansible Tower API
Home-page: https://github.com/mkanoor/receptor-catalog
Author: Red Hat Insights
Author-email: support@redhat.com
License: Apache
Platform: UNKNOWN
Classifier: Programming Language :: Python :: 3
Requires-Dist: aiohttp
Requires-Dist: jmespath
Provides-Extra: dev
Requires-Dist: pytest ; extra == 'dev'
Requires-Dist: flake8 ; extra == 'dev'
Requires-Dist: pylint ; extra == 'dev'
Requires-Dist: black ; extra == 'dev'
